{"stats":{"total":416,"passed":410,"new":3,"broken":2,"failed":4},"status":"failed","newTests":[{"id":"0a4149c6f6aaabc7c0223f90111c48d1","name":"Plain_GET_without_upgrade_returns_400","status":"passed","duration":0},{"id":"55175a527d82438d83e60961369f6462","name":"Remote Playwright WS session opens example.com","status":"passed","duration":3771},{"id":"ec169889055195216df5122f2909f6f1","name":"TestWsProxyRejectsPlainGet","status":"passed","duration":0}],"flakyTests":[],"retryTests":[],"checks":[],"name":"selenoid-tests Tests","duration":616331,"createdAt":1783613189361,"plugin":"Awesome","meta":{"reportId":"a948617b-de63-4697-9ea4-ab19a9f1b1a6","singleFile":false,"withTestResultsLinks":true},"pluginId":"awesome","pullRequestHref":"","jobHref":"https://github.com/qa-guru/selenoid-tests/actions/runs/29031424733","href":"awesome/"}