{"stats":{"total":21,"passed":19,"flaky":2,"failed":2},"status":"failed","newTests":[],"flakyTests":[{"id":"700edcfcf03ffb0659b191be1052e9d8","name":"GET /status used counter tracks session lifecycle","status":"failed","duration":15809},{"id":"5c4838147d78add529ed919dce8d3077","name":"GET /logs/{sessionId} without WebSocket upgrade returns 400","status":"failed","duration":2583}],"retryTests":[],"checks":[],"name":"selenoid-tests Tests","duration":84962,"createdAt":1783519356626,"plugin":"Awesome","meta":{"reportId":"e880047f-9073-4f19-83ff-63660c0caadc","singleFile":false,"withTestResultsLinks":true},"pluginId":"awesome","pullRequestHref":"","jobHref":"https://github.com/qa-guru/selenoid-tests/actions/runs/28948496213","href":"awesome/"}