{"stats":{"total":50,"broken":14,"failed":36,"flaky":5},"status":"failed","newTests":[],"flakyTests":[{"id":"f08e470cb1f32be5770b349922a1a5c5","name":"SSE indicator uses ok styling when connected","status":"broken","duration":709},{"id":"9771abb2e0728f91d15f764b17f203d2","name":"Dashboard reload keeps CONNECTED indicators","status":"broken","duration":723},{"id":"340e252e7d545bb819ca501c06b10399","name":"SSE and SELENOID stay CONNECTED on stable stack","status":"broken","duration":689},{"id":"7e67dd07d526a4479d8ee7e3922a3fe1","name":"Active hub session appears in dashboard sessions list","status":"failed","duration":863},{"id":"ee581b46f829c1616736bc538a76c294","name":"GET /vnc/{sessionId} without WebSocket upgrade returns 400 when enableVNC=true","status":"failed","duration":887}],"retryTests":[],"checks":[],"name":"selenoid-tests Tests Dashboard","duration":41882,"createdAt":1783685043838,"plugin":"Dashboard","meta":{"reportId":"bc6631ba-7809-4a7b-a3db-2c6fc6d9bcb8","singleFile":false},"pluginId":"dashboard","pullRequestHref":"","jobHref":"https://github.com/qa-guru/selenoid-tests/actions/runs/29091326821","href":"dashboard/"}