{"stats":{"total":466,"passed":465,"flaky":1,"failed":1},"status":"failed","newTests":[],"flakyTests":[{"id":"8ea62d248890fbb6982ae6b0603f5bf0","name":"Capabilities chrome session shows connected VNC and navigates remote browser","status":"failed","duration":5388}],"retryTests":[],"checks":[],"name":"selenoid-tests Tests Dashboard","duration":83746,"createdAt":1784382833482,"plugin":"Dashboard","meta":{"reportId":"0781cd5a-a5d2-4e22-a107-2482ce8fb3ac","singleFile":false},"pluginId":"dashboard","pullRequestHref":"","jobHref":"https://github.com/qa-guru/selenoid-tests/actions/runs/29646865459","href":"dashboard/"}